hnbookextractor/__init__.py
hnbookextractor/main.py
hnbookextractor/prompts.py
hnbookextractor-2025.12.21171700.dist-info/METADATA
hnbookextractor-2025.12.21171700.dist-info/WHEEL
hnbookextractor-2025.12.21171700.dist-info/top_level.txt
hnbookextractor-2025.12.21171700.dist-info/RECORD
