Metadata-Version: 2.4
Name: hnbookextractor
Version: 2025.12.21171700
Summary: A new package is designed to analyze user-submitted text about Hacker News discussions to identify and extract a structured list of books mentioned in 2025. It leverages language models to recognize b
Author-email: hnbookextractor <hi@eugene.plus>
License: MIT
Project-URL: Homepage, https://github.com/chigwell/hnbookextractor
Requires-Python: >=3.9
Requires-Dist: langchain-llm7>=0.0.0
Requires-Dist: llmatch-messages>=0.0.0
Requires-Dist: langchain-core>=0.3.0
